{
  "last_updated": "2025-11-07T21:04:13.895612",
  "player_id": 1629023,
  "player_name": "P.J. Washington",
  "season": "2025-26",
  "data": {
    "SeasonTotalsRegularSeason": [
      {
        "PLAYER_ID": 1629023,
        "SEASON_ID": "2019-20",
        "LEAGUE_ID": "00",
        "TEAM_ID": 1610612766,
        "TEAM_ABBREVIATION": "CHA",
        "PLAYER_AGE": 21.0,
        "GP": 58,
        "GS": 57,
        "MIN": 1759,
        "FGM": 268,
        "FGA": 589,
        "FG_PCT": 0.455,
        "FG3M": 86,
        "FG3A": 230,
        "FG3_PCT": 0.374,
        "FTM": 88,
        "FTA": 136,
        "FT_PCT": 0.647,
        "OREB": 58,
        "DREB": 258,
        "REB": 316,
        "AST": 123,
        "STL": 51,
        "BLK": 44,
        "TOV": 93,
        "PF": 158,
        "PTS": 710
      },
      {
        "PLAYER_ID": 1629023,
        "SEASON_ID": "2020-21",
        "LEAGUE_ID": "00",
        "TEAM_ID": 1610612766,
        "TEAM_ABBREVIATION": "CHA",
        "PLAYER_AGE": 22.0,
        "GP": 64,
        "GS": 61,
        "MIN": 1954,
        "FGM": 302,
        "FGA": 686,
        "FG_PCT": 0.44,
        "FG3M": 112,
        "FG3A": 290,
        "FG3_PCT": 0.386,
        "FTM": 108,
        "FTA": 145,
        "FT_PCT": 0.745,
        "OREB": 93,
        "DREB": 325,
        "REB": 418,
        "AST": 161,
        "STL": 69,
        "BLK": 79,
        "TOV": 128,
        "PF": 171,
        "PTS": 824
      },
      {
        "PLAYER_ID": 1629023,
        "SEASON_ID": "2021-22",
        "LEAGUE_ID": "00",
        "TEAM_ID": 1610612766,
        "TEAM_ABBREVIATION": "CHA",
        "PLAYER_AGE": 23.0,
        "GP": 65,
        "GS": 28,
        "MIN": 1768,
        "FGM": 250,
        "FGA": 532,
        "FG_PCT": 0.47,
        "FG3M": 110,
        "FG3A": 301,
        "FG3_PCT": 0.365,
        "FTM": 58,
        "FTA": 81,
        "FT_PCT": 0.716,
        "OREB": 82,
        "DREB": 255,
        "REB": 337,
        "AST": 147,
        "STL": 57,
        "BLK": 61,
        "TOV": 82,
        "PF": 152,
        "PTS": 668
      },
      {
        "PLAYER_ID": 1629023,
        "SEASON_ID": "2022-23",
        "LEAGUE_ID": "00",
        "TEAM_ID": 1610612766,
        "TEAM_ABBREVIATION": "CHA",
        "PLAYER_AGE": 24.0,
        "GP": 73,
        "GS": 73,
        "MIN": 2380,
        "FGM": 434,
        "FGA": 978,
        "FG_PCT": 0.444,
        "FG3M": 149,
        "FG3A": 428,
        "FG3_PCT": 0.348,
        "FTM": 127,
        "FTA": 174,
        "FT_PCT": 0.73,
        "OREB": 73,
        "DREB": 285,
        "REB": 358,
        "AST": 175,
        "STL": 66,
        "BLK": 79,
        "TOV": 110,
        "PF": 193,
        "PTS": 1144
      },
      {
        "PLAYER_ID": 1629023,
        "SEASON_ID": "2023-24",
        "LEAGUE_ID": "00",
        "TEAM_ID": 1610612766,
        "TEAM_ABBREVIATION": "CHA",
        "PLAYER_AGE": 25.0,
        "GP": 44,
        "GS": 17,
        "MIN": 1286,
        "FGM": 227,
        "FGA": 509,
        "FG_PCT": 0.446,
        "FG3M": 79,
        "FG3A": 244,
        "FG3_PCT": 0.324,
        "FTM": 67,
        "FTA": 94,
        "FT_PCT": 0.713,
        "OREB": 53,
        "DREB": 179,
        "REB": 232,
        "AST": 97,
        "STL": 38,
        "BLK": 32,
        "TOV": 66,
        "PF": 112,
        "PTS": 600
      },
      {
        "PLAYER_ID": 1629023,
        "SEASON_ID": "2023-24",
        "LEAGUE_ID": "00",
        "TEAM_ID": 1610612742,
        "TEAM_ABBREVIATION": "DAL",
        "PLAYER_AGE": 25.0,
        "GP": 29,
        "GS": 28,
        "MIN": 935,
        "FGM": 127,
        "FGA": 302,
        "FG_PCT": 0.421,
        "FG3M": 53,
        "FG3A": 169,
        "FG3_PCT": 0.314,
        "FTM": 32,
        "FTA": 51,
        "FT_PCT": 0.627,
        "OREB": 32,
        "DREB": 147,
        "REB": 179,
        "AST": 44,
        "STL": 34,
        "BLK": 27,
        "TOV": 30,
        "PF": 57,
        "PTS": 339
      },
      {
        "PLAYER_ID": 1629023,
        "SEASON_ID": "2023-24",
        "LEAGUE_ID": "00",
        "TEAM_ID": 0,
        "TEAM_ABBREVIATION": "TOT",
        "PLAYER_AGE": 25.0,
        "GP": 73,
        "GS": 45,
        "MIN": 2221,
        "FGM": 354,
        "FGA": 811,
        "FG_PCT": 0.436,
        "FG3M": 132,
        "FG3A": 413,
        "FG3_PCT": 0.32,
        "FTM": 99,
        "FTA": 145,
        "FT_PCT": 0.683,
        "OREB": 85,
        "DREB": 326,
        "REB": 411,
        "AST": 141,
        "STL": 72,
        "BLK": 59,
        "TOV": 96,
        "PF": 169,
        "PTS": 939
      },
      {
        "PLAYER_ID": 1629023,
        "SEASON_ID": "2024-25",
        "LEAGUE_ID": "00",
        "TEAM_ID": 1610612742,
        "TEAM_ABBREVIATION": "DAL",
        "PLAYER_AGE": 26.0,
        "GP": 57,
        "GS": 56,
        "MIN": 1835,
        "FGM": 301,
        "FGA": 665,
        "FG_PCT": 0.453,
        "FG3M": 91,
        "FG3A": 239,
        "FG3_PCT": 0.381,
        "FTM": 143,
        "FTA": 198,
        "FT_PCT": 0.722,
        "OREB": 82,
        "DREB": 360,
        "REB": 442,
        "AST": 131,
        "STL": 63,
        "BLK": 60,
        "TOV": 118,
        "PF": 131,
        "PTS": 836
      },
      {
        "PLAYER_ID": 1629023,
        "SEASON_ID": "2025-26",
        "LEAGUE_ID": "00",
        "TEAM_ID": 1610612742,
        "TEAM_ABBREVIATION": "DAL",
        "PLAYER_AGE": 27.0,
        "GP": 8,
        "GS": 8,
        "MIN": 277,
        "FGM": 47,
        "FGA": 103,
        "FG_PCT": 0.456,
        "FG3M": 9,
        "FG3A": 32,
        "FG3_PCT": 0.281,
        "FTM": 23,
        "FTA": 39,
        "FT_PCT": 0.59,
        "OREB": 10,
        "DREB": 59,
        "REB": 69,
        "AST": 21,
        "STL": 7,
        "BLK": 11,
        "TOV": 24,
        "PF": 19,
        "PTS": 126
      }
    ],
    "CareerTotalsRegularSeason": [
      {
        "PLAYER_ID": 1629023,
        "LEAGUE_ID": "00",
        "TEAM_ID": 0,
        "GP": 398,
        "GS": 328,
        "MIN": 12192,
        "FGM": 1956,
        "FGA": 4364,
        "FG_PCT": 0.448212648945,
        "FG3M": 689,
        "FG3A": 1933,
        "FG3_PCT": 0.356440765649,
        "FTM": 646,
        "FTA": 918,
        "FT_PCT": 0.703703703703,
        "OREB": 483,
        "DREB": 1868,
        "REB": 2351,
        "AST": 899,
        "STL": 385,
        "BLK": 393,
        "TOV": 651,
        "PF": 993,
        "PTS": 5247
      }
    ],
    "SeasonTotalsPostSeason": [
      {
        "PLAYER_ID": 1629023,
        "SEASON_ID": "2023-24",
        "LEAGUE_ID": "00",
        "TEAM_ID": 1610612742,
        "TEAM_ABBREVIATION": "DAL",
        "PLAYER_AGE": 25.0,
        "GP": 22,
        "GS": 22,
        "MIN": 785,
        "FGM": 100,
        "FGA": 234,
        "FG_PCT": 0.427,
        "FG3M": 47,
        "FG3A": 135,
        "FG3_PCT": 0.348,
        "FTM": 39,
        "FTA": 55,
        "FT_PCT": 0.709,
        "OREB": 33,
        "DREB": 112,
        "REB": 145,
        "AST": 31,
        "STL": 16,
        "BLK": 17,
        "TOV": 32,
        "PF": 67,
        "PTS": 286
      }
    ],
    "CareerTotalsPostSeason": [
      {
        "PLAYER_ID": 1629023,
        "LEAGUE_ID": "00",
        "TEAM_ID": 0,
        "GP": 22,
        "GS": 22,
        "MIN": 784,
        "FGM": 100,
        "FGA": 234,
        "FG_PCT": 0.42735042735,
        "FG3M": 47,
        "FG3A": 135,
        "FG3_PCT": 0.348148148148,
        "FTM": 39,
        "FTA": 55,
        "FT_PCT": 0.70909090909,
        "OREB": 33,
        "DREB": 112,
        "REB": 145,
        "AST": 31,
        "STL": 16,
        "BLK": 17,
        "TOV": 32,
        "PF": 67,
        "PTS": 286
      }
    ],
    "SeasonTotalsAllStarSeason": [],
    "CareerTotalsAllStarSeason": [],
    "SeasonTotalsCollegeSeason": [
      {
        "PLAYER_ID": 1629023,
        "SEASON_ID": "2018-19",
        "LEAGUE_ID": "00",
        "ORGANIZATION_ID": 2852,
        "SCHOOL_NAME": "Kentucky",
        "PLAYER_AGE": 20.0,
        "GP": 35,
        "GS": 33,
        "MIN": 1024,
        "FGM": 190,
        "FGA": 364,
        "FG_PCT": 0.522,
        "FG3M": 33,
        "FG3A": 78,
        "FG3_PCT": 0.423,
        "FTM": 118,
        "FTA": 178,
        "FT_PCT": 0.663,
        "OREB": 81,
        "DREB": 183,
        "REB": 264,
        "AST": 63,
        "STL": 30,
        "BLK": 43,
        "TOV": 69,
        "PF": 86,
        "PTS": 531
      },
      {
        "PLAYER_ID": 1629023,
        "SEASON_ID": "2017-18",
        "LEAGUE_ID": "00",
        "ORGANIZATION_ID": 2852,
        "SCHOOL_NAME": "Kentucky",
        "PLAYER_AGE": 19.0,
        "GP": 37,
        "GS": 30,
        "MIN": 1012,
        "FGM": 135,
        "FGA": 260,
        "FG_PCT": 0.519,
        "FG3M": 5,
        "FG3A": 21,
        "FG3_PCT": 0.238,
        "FTM": 126,
        "FTA": 208,
        "FT_PCT": 0.606,
        "OREB": 67,
        "DREB": 144,
        "REB": 211,
        "AST": 57,
        "STL": 28,
        "BLK": 31,
        "TOV": 71,
        "PF": 100,
        "PTS": 401
      }
    ],
    "CareerTotalsCollegeSeason": [
      {
        "PLAYER_ID": 1629023,
        "LEAGUE_ID": "00",
        "ORGANIZATION_ID": 0,
        "GP": 72,
        "GS": 63,
        "MIN": 2036,
        "FGM": 325,
        "FGA": 624,
        "FG_PCT": 0.521,
        "FG3M": 38,
        "FG3A": 99,
        "FG3_PCT": 0.384,
        "FTM": 244,
        "FTA": 386,
        "FT_PCT": 0.632,
        "OREB": 148,
        "DREB": 327,
        "REB": 475,
        "AST": 120,
        "STL": 58,
        "BLK": 74,
        "TOV": 140,
        "PF": 186,
        "PTS": 932
      }
    ],
    "SeasonTotalsShowcaseSeason": [],
    "CareerTotalsShowcaseSeason": [],
    "SeasonRankingsRegularSeason": [
      {
        "PLAYER_ID": 1629023,
        "SEASON_ID": "2019-20",
        "LEAGUE_ID": "00",
        "TEAM_ID": 1610612766,
        "TEAM_ABBREVIATION": "CHA",
        "PLAYER_AGE": "NR",
        "GP": "NR",
        "GS": "NR",
        "RANK_MIN": 100,
        "RANK_FGM": 119,
        "RANK_FGA": 117,
        "RANK_FG_PCT": 67,
        "RANK_FG3M": 116,
        "RANK_FG3A": 123,
        "RANK_FG3_PCT": 73,
        "RANK_FTM": 140,
        "RANK_FTA": 118,
        "RANK_FT_PCT": null,
        "RANK_OREB": 128,
        "RANK_DREB": 84,
        "RANK_REB": 91,
        "RANK_AST": 131,
        "RANK_STL": 114,
        "RANK_BLK": 63,
        "RANK_TOV": 101,
        "RANK_PTS": 123,
        "RANK_EFF": 139
      },
      {
        "PLAYER_ID": 1629023,
        "SEASON_ID": "2020-21",
        "LEAGUE_ID": "00",
        "TEAM_ID": 1610612766,
        "TEAM_ABBREVIATION": "CHA",
        "PLAYER_AGE": "NR",
        "GP": "NR",
        "GS": "NR",
        "RANK_MIN": 56,
        "RANK_FGM": 95,
        "RANK_FGA": 79,
        "RANK_FG_PCT": 91,
        "RANK_FG3M": 82,
        "RANK_FG3A": 80,
        "RANK_FG3_PCT": 81,
        "RANK_FTM": 112,
        "RANK_FTA": 103,
        "RANK_FT_PCT": null,
        "RANK_OREB": 55,
        "RANK_DREB": 37,
        "RANK_REB": 41,
        "RANK_AST": 106,
        "RANK_STL": 47,
        "RANK_BLK": 14,
        "RANK_TOV": 45,
        "RANK_PTS": 91,
        "RANK_EFF": 77
      },
      {
        "PLAYER_ID": 1629023,
        "SEASON_ID": "2021-22",
        "LEAGUE_ID": "00",
        "TEAM_ID": 1610612766,
        "TEAM_ABBREVIATION": "CHA",
        "PLAYER_AGE": "NR",
        "GP": "NR",
        "GS": "NR",
        "RANK_MIN": 135,
        "RANK_FGM": 158,
        "RANK_FGA": 164,
        "RANK_FG_PCT": null,
        "RANK_FG3M": 103,
        "RANK_FG3A": 102,
        "RANK_FG3_PCT": 84,
        "RANK_FTM": 241,
        "RANK_FTA": 231,
        "RANK_FT_PCT": null,
        "RANK_OREB": 87,
        "RANK_DREB": 101,
        "RANK_REB": 99,
        "RANK_AST": 150,
        "RANK_STL": 113,
        "RANK_BLK": 35,
        "RANK_TOV": 134,
        "RANK_PTS": 158,
        "RANK_EFF": 135
      },
      {
        "PLAYER_ID": 1629023,
        "SEASON_ID": "2022-23",
        "LEAGUE_ID": "00",
        "TEAM_ID": 1610612766,
        "TEAM_ABBREVIATION": "CHA",
        "PLAYER_AGE": "NR",
        "GP": "NR",
        "GS": "NR",
        "RANK_MIN": 40,
        "RANK_FGM": 65,
        "RANK_FGA": 54,
        "RANK_FG_PCT": 95,
        "RANK_FG3M": 53,
        "RANK_FG3A": 38,
        "RANK_FG3_PCT": 115,
        "RANK_FTM": 119,
        "RANK_FTA": 112,
        "RANK_FT_PCT": 108,
        "RANK_OREB": 105,
        "RANK_DREB": 77,
        "RANK_REB": 83,
        "RANK_AST": 126,
        "RANK_STL": 75,
        "RANK_BLK": 21,
        "RANK_TOV": 100,
        "RANK_PTS": 75,
        "RANK_EFF": 95
      },
      {
        "PLAYER_ID": 1629023,
        "SEASON_ID": "2023-24",
        "LEAGUE_ID": "00",
        "TEAM_ID": 1610612742,
        "TEAM_ABBREVIATION": "DAL",
        "PLAYER_AGE": "NR",
        "GP": "NR",
        "GS": "NR",
        "RANK_MIN": 66,
        "RANK_FGM": 104,
        "RANK_FGA": 91,
        "RANK_FG_PCT": 116,
        "RANK_FG3M": 82,
        "RANK_FG3A": 50,
        "RANK_FG3_PCT": 155,
        "RANK_FTM": 143,
        "RANK_FTA": 127,
        "RANK_FT_PCT": null,
        "RANK_OREB": 85,
        "RANK_DREB": 57,
        "RANK_REB": 64,
        "RANK_AST": 156,
        "RANK_STL": 58,
        "RANK_BLK": 48,
        "RANK_TOV": 120,
        "RANK_PTS": 106,
        "RANK_EFF": 114
      },
      {
        "PLAYER_ID": 1629023,
        "SEASON_ID": "2024-25",
        "LEAGUE_ID": "00",
        "TEAM_ID": 1610612742,
        "TEAM_ABBREVIATION": "DAL",
        "PLAYER_AGE": "NR",
        "GP": "NR",
        "GS": "NR",
        "RANK_MIN": 122,
        "RANK_FGM": 115,
        "RANK_FGA": 110,
        "RANK_FG_PCT": 81,
        "RANK_FG3M": 152,
        "RANK_FG3A": 165,
        "RANK_FG3_PCT": 66,
        "RANK_FTM": 91,
        "RANK_FTA": 82,
        "RANK_FT_PCT": 95,
        "RANK_OREB": 100,
        "RANK_DREB": 38,
        "RANK_REB": 51,
        "RANK_AST": 174,
        "RANK_STL": 104,
        "RANK_BLK": 44,
        "RANK_TOV": 79,
        "RANK_PTS": 113,
        "RANK_EFF": 106
      },
      {
        "PLAYER_ID": 1629023,
        "SEASON_ID": "2025-26",
        "LEAGUE_ID": "00",
        "TEAM_ID": 1610612742,
        "TEAM_ABBREVIATION": "DAL",
        "PLAYER_AGE": "NR",
        "GP": "NR",
        "GS": "NR",
        "RANK_MIN": 16,
        "RANK_FGM": 54,
        "RANK_FGA": 53,
        "RANK_FG_PCT": 106,
        "RANK_FG3M": 146,
        "RANK_FG3A": 105,
        "RANK_FG3_PCT": 172,
        "RANK_FTM": 60,
        "RANK_FTA": 38,
        "RANK_FT_PCT": 128,
        "RANK_OREB": 86,
        "RANK_DREB": 10,
        "RANK_REB": 15,
        "RANK_AST": 99,
        "RANK_STL": 99,
        "RANK_BLK": 12,
        "RANK_TOV": 14,
        "RANK_PTS": 68,
        "RANK_EFF": 69
      }
    ],
    "SeasonRankingsPostSeason": [
      {
        "PLAYER_ID": 1629023,
        "SEASON_ID": "2023-24",
        "LEAGUE_ID": "00",
        "TEAM_ID": 1610612742,
        "TEAM_ABBREVIATION": "DAL",
        "PLAYER_AGE": "NR",
        "GP": "NR",
        "GS": "NR",
        "RANK_MIN": 3,
        "RANK_FGM": 16,
        "RANK_FGA": 11,
        "RANK_FG_PCT": 51,
        "RANK_FG3M": 5,
        "RANK_FG3A": 6,
        "RANK_FG3_PCT": 57,
        "RANK_FTM": 14,
        "RANK_FTA": 16,
        "RANK_FT_PCT": 47,
        "RANK_OREB": 12,
        "RANK_DREB": 5,
        "RANK_REB": 7,
        "RANK_AST": 37,
        "RANK_STL": 14,
        "RANK_BLK": 9,
        "RANK_TOV": 10,
        "RANK_PTS": 14,
        "RANK_EFF": 15
      }
    ],
    "SeasonHighs": [
      {
        "PLAYER_ID": 1629023,
        "GAME_ID": "0022500160",
        "GAME_DATE": "Nov 03 2025",
        "VS_TEAM_ID": 1610612745,
        "VS_TEAM_CITY": "Houston",
        "VS_TEAM_NAME": "Rockets",
        "VS_TEAM_ABBREVIATION": "HOU",
        "STAT": "PTS",
        "STAT_VALUE": 29,
        "STAT_ORDER": 1,
        "DATE_EST": "2025-11-03T00:00:00"
      },
      {
        "PLAYER_ID": 1629023,
        "GAME_ID": "0022500160",
        "GAME_DATE": "Nov 03 2025",
        "VS_TEAM_ID": 1610612745,
        "VS_TEAM_CITY": "Houston",
        "VS_TEAM_NAME": "Rockets",
        "VS_TEAM_ABBREVIATION": "HOU",
        "STAT": "REB",
        "STAT_VALUE": 12,
        "STAT_ORDER": 2,
        "DATE_EST": "2025-11-03T00:00:00"
      },
      {
        "PLAYER_ID": 1629023,
        "GAME_ID": "0022500177",
        "GAME_DATE": "Nov 05 2025",
        "VS_TEAM_ID": 1610612740,
        "VS_TEAM_CITY": "New Orleans",
        "VS_TEAM_NAME": "Pelicans",
        "VS_TEAM_ABBREVIATION": "NOP",
        "STAT": "OREB",
        "STAT_VALUE": 3,
        "STAT_ORDER": 3,
        "DATE_EST": "2025-11-05T00:00:00"
      },
      {
        "PLAYER_ID": 1629023,
        "GAME_ID": "0022500160",
        "GAME_DATE": "Nov 03 2025",
        "VS_TEAM_ID": 1610612745,
        "VS_TEAM_CITY": "Houston",
        "VS_TEAM_NAME": "Rockets",
        "VS_TEAM_ABBREVIATION": "HOU",
        "STAT": "DREB",
        "STAT_VALUE": 12,
        "STAT_ORDER": 4,
        "DATE_EST": "2025-11-03T00:00:00"
      },
      {
        "PLAYER_ID": 1629023,
        "GAME_ID": "0022500147",
        "GAME_DATE": "Nov 01 2025",
        "VS_TEAM_ID": 1610612765,
        "VS_TEAM_CITY": "Detroit",
        "VS_TEAM_NAME": "Pistons",
        "VS_TEAM_ABBREVIATION": "DET",
        "STAT": "AST",
        "STAT_VALUE": 5,
        "STAT_ORDER": 5,
        "DATE_EST": "2025-11-01T00:00:00"
      },
      {
        "PLAYER_ID": 1629023,
        "GAME_ID": "0022500111",
        "GAME_DATE": "Oct 26 2025",
        "VS_TEAM_ID": 1610612761,
        "VS_TEAM_CITY": "Toronto",
        "VS_TEAM_NAME": "Raptors",
        "VS_TEAM_ABBREVIATION": "TOR",
        "STAT": "AST",
        "STAT_VALUE": 5,
        "STAT_ORDER": 5,
        "DATE_EST": "2025-10-26T00:00:00"
      },
      {
        "PLAYER_ID": 1629023,
        "GAME_ID": "0022500160",
        "GAME_DATE": "Nov 03 2025",
        "VS_TEAM_ID": 1610612745,
        "VS_TEAM_CITY": "Houston",
        "VS_TEAM_NAME": "Rockets",
        "VS_TEAM_ABBREVIATION": "HOU",
        "STAT": "STL",
        "STAT_VALUE": 2,
        "STAT_ORDER": 6,
        "DATE_EST": "2025-11-03T00:00:00"
      },
      {
        "PLAYER_ID": 1629023,
        "GAME_ID": "0022500096",
        "GAME_DATE": "Oct 24 2025",
        "VS_TEAM_ID": 1610612764,
        "VS_TEAM_CITY": "Washington",
        "VS_TEAM_NAME": "Wizards",
        "VS_TEAM_ABBREVIATION": "WAS",
        "STAT": "STL",
        "STAT_VALUE": 2,
        "STAT_ORDER": 6,
        "DATE_EST": "2025-10-24T00:00:00"
      },
      {
        "PLAYER_ID": 1629023,
        "GAME_ID": "0022500147",
        "GAME_DATE": "Nov 01 2025",
        "VS_TEAM_ID": 1610612765,
        "VS_TEAM_CITY": "Detroit",
        "VS_TEAM_NAME": "Pistons",
        "VS_TEAM_ABBREVIATION": "DET",
        "STAT": "BLK",
        "STAT_VALUE": 3,
        "STAT_ORDER": 7,
        "DATE_EST": "2025-11-01T00:00:00"
      },
      {
        "PLAYER_ID": 1629023,
        "GAME_ID": "0022500160",
        "GAME_DATE": "Nov 03 2025",
        "VS_TEAM_ID": 1610612745,
        "VS_TEAM_CITY": "Houston",
        "VS_TEAM_NAME": "Rockets",
        "VS_TEAM_ABBREVIATION": "HOU",
        "STAT": "FGM",
        "STAT_VALUE": 11,
        "STAT_ORDER": 8,
        "DATE_EST": "2025-11-03T00:00:00"
      },
      {
        "PLAYER_ID": 1629023,
        "GAME_ID": "0022500160",
        "GAME_DATE": "Nov 03 2025",
        "VS_TEAM_ID": 1610612745,
        "VS_TEAM_CITY": "Houston",
        "VS_TEAM_NAME": "Rockets",
        "VS_TEAM_ABBREVIATION": "HOU",
        "STAT": "FGA",
        "STAT_VALUE": 20,
        "STAT_ORDER": 9,
        "DATE_EST": "2025-11-03T00:00:00"
      },
      {
        "PLAYER_ID": 1629023,
        "GAME_ID": "0022500119",
        "GAME_DATE": "Oct 27 2025",
        "VS_TEAM_ID": 1610612760,
        "VS_TEAM_CITY": "Oklahoma City",
        "VS_TEAM_NAME": "Thunder",
        "VS_TEAM_ABBREVIATION": "OKC",
        "STAT": "FG3M",
        "STAT_VALUE": 2,
        "STAT_ORDER": 10,
        "DATE_EST": "2025-10-27T00:00:00"
      },
      {
        "PLAYER_ID": 1629023,
        "GAME_ID": "0022500096",
        "GAME_DATE": "Oct 24 2025",
        "VS_TEAM_ID": 1610612764,
        "VS_TEAM_CITY": "Washington",
        "VS_TEAM_NAME": "Wizards",
        "VS_TEAM_ABBREVIATION": "WAS",
        "STAT": "FG3M",
        "STAT_VALUE": 2,
        "STAT_ORDER": 10,
        "DATE_EST": "2025-10-24T00:00:00"
      },
      {
        "PLAYER_ID": 1629023,
        "GAME_ID": "0022500004",
        "GAME_DATE": "Oct 22 2025",
        "VS_TEAM_ID": 1610612759,
        "VS_TEAM_CITY": "San Antonio",
        "VS_TEAM_NAME": "Spurs",
        "VS_TEAM_ABBREVIATION": "SAS",
        "STAT": "FG3M",
        "STAT_VALUE": 2,
        "STAT_ORDER": 10,
        "DATE_EST": "2025-10-22T00:00:00"
      },
      {
        "PLAYER_ID": 1629023,
        "GAME_ID": "0022500147",
        "GAME_DATE": "Nov 01 2025",
        "VS_TEAM_ID": 1610612765,
        "VS_TEAM_CITY": "Detroit",
        "VS_TEAM_NAME": "Pistons",
        "VS_TEAM_ABBREVIATION": "DET",
        "STAT": "FG3A",
        "STAT_VALUE": 6,
        "STAT_ORDER": 11,
        "DATE_EST": "2025-11-01T00:00:00"
      },
      {
        "PLAYER_ID": 1629023,
        "GAME_ID": "0022500160",
        "GAME_DATE": "Nov 03 2025",
        "VS_TEAM_ID": 1610612745,
        "VS_TEAM_CITY": "Houston",
        "VS_TEAM_NAME": "Rockets",
        "VS_TEAM_ABBREVIATION": "HOU",
        "STAT": "FTM",
        "STAT_VALUE": 6,
        "STAT_ORDER": 12,
        "DATE_EST": "2025-11-03T00:00:00"
      },
      {
        "PLAYER_ID": 1629023,
        "GAME_ID": "0022500160",
        "GAME_DATE": "Nov 03 2025",
        "VS_TEAM_ID": 1610612745,
        "VS_TEAM_CITY": "Houston",
        "VS_TEAM_NAME": "Rockets",
        "VS_TEAM_ABBREVIATION": "HOU",
        "STAT": "FTA",
        "STAT_VALUE": 10,
        "STAT_ORDER": 13,
        "DATE_EST": "2025-11-03T00:00:00"
      }
    ],
    "CareerHighs": [
      {
        "PLAYER_ID": 1629023,
        "GAME_ID": "0022300647",
        "GAME_DATE": "Jan 27 2024",
        "VS_TEAM_ID": 1610612762,
        "VS_TEAM_CITY": "Utah",
        "VS_TEAM_NAME": "Jazz",
        "VS_TEAM_ABBREVIATION": "UTA",
        "STAT": "PTS",
        "STAT_VALUE": 43,
        "STAT_ORDER": 1,
        "DATE_EST": "2024-01-27T00:00:00"
      },
      {
        "PLAYER_ID": 1629023,
        "GAME_ID": "0022201134",
        "GAME_DATE": "Mar 28 2023",
        "VS_TEAM_ID": 1610612760,
        "VS_TEAM_CITY": "Oklahoma City",
        "VS_TEAM_NAME": "Thunder",
        "VS_TEAM_ABBREVIATION": "OKC",
        "STAT": "PTS",
        "STAT_VALUE": 43,
        "STAT_ORDER": 1,
        "DATE_EST": "2023-03-28T00:00:00"
      },
      {
        "PLAYER_ID": 1629023,
        "GAME_ID": "0022400625",
        "GAME_DATE": "Jan 23 2025",
        "VS_TEAM_ID": 1610612760,
        "VS_TEAM_CITY": "Oklahoma City",
        "VS_TEAM_NAME": "Thunder",
        "VS_TEAM_ABBREVIATION": "OKC",
        "STAT": "REB",
        "STAT_VALUE": 19,
        "STAT_ORDER": 2,
        "DATE_EST": "2025-01-23T00:00:00"
      },
      {
        "PLAYER_ID": 1629023,
        "GAME_ID": "0022400242",
        "GAME_DATE": "Nov 17 2024",
        "VS_TEAM_ID": 1610612760,
        "VS_TEAM_CITY": "Oklahoma City",
        "VS_TEAM_NAME": "Thunder",
        "VS_TEAM_ABBREVIATION": "OKC",
        "STAT": "OREB",
        "STAT_VALUE": 6,
        "STAT_ORDER": 3,
        "DATE_EST": "2024-11-17T00:00:00"
      },
      {
        "PLAYER_ID": 1629023,
        "GAME_ID": "0022000032",
        "GAME_DATE": "Dec 27 2020",
        "VS_TEAM_ID": 1610612751,
        "VS_TEAM_CITY": "Brooklyn",
        "VS_TEAM_NAME": "Nets",
        "VS_TEAM_ABBREVIATION": "BKN",
        "STAT": "OREB",
        "STAT_VALUE": 6,
        "STAT_ORDER": 3,
        "DATE_EST": "2020-12-27T00:00:00"
      },
      {
        "PLAYER_ID": 1629023,
        "GAME_ID": "0022400625",
        "GAME_DATE": "Jan 23 2025",
        "VS_TEAM_ID": 1610612760,
        "VS_TEAM_CITY": "Oklahoma City",
        "VS_TEAM_NAME": "Thunder",
        "VS_TEAM_ABBREVIATION": "OKC",
        "STAT": "DREB",
        "STAT_VALUE": 17,
        "STAT_ORDER": 4,
        "DATE_EST": "2025-01-23T00:00:00"
      },
      {
        "PLAYER_ID": 1629023,
        "GAME_ID": "0022400670",
        "GAME_DATE": "Jan 29 2025",
        "VS_TEAM_ID": 1610612740,
        "VS_TEAM_CITY": "New Orleans",
        "VS_TEAM_NAME": "Pelicans",
        "VS_TEAM_ABBREVIATION": "NOP",
        "STAT": "AST",
        "STAT_VALUE": 8,
        "STAT_ORDER": 5,
        "DATE_EST": "2025-01-29T00:00:00"
      },
      {
        "PLAYER_ID": 1629023,
        "GAME_ID": "0022301097",
        "GAME_DATE": "Apr 05 2024",
        "VS_TEAM_ID": 1610612744,
        "VS_TEAM_CITY": "Golden State",
        "VS_TEAM_NAME": "Warriors",
        "VS_TEAM_ABBREVIATION": "GSW",
        "STAT": "STL",
        "STAT_VALUE": 5,
        "STAT_ORDER": 6,
        "DATE_EST": "2024-04-05T00:00:00"
      },
      {
        "PLAYER_ID": 1629023,
        "GAME_ID": "0022000134",
        "GAME_DATE": "Jan 09 2021",
        "VS_TEAM_ID": 1610612737,
        "VS_TEAM_CITY": "Atlanta",
        "VS_TEAM_NAME": "Hawks",
        "VS_TEAM_ABBREVIATION": "ATL",
        "STAT": "BLK",
        "STAT_VALUE": 6,
        "STAT_ORDER": 7,
        "DATE_EST": "2021-01-09T00:00:00"
      },
      {
        "PLAYER_ID": 1629023,
        "GAME_ID": "0022300647",
        "GAME_DATE": "Jan 27 2024",
        "VS_TEAM_ID": 1610612762,
        "VS_TEAM_CITY": "Utah",
        "VS_TEAM_NAME": "Jazz",
        "VS_TEAM_ABBREVIATION": "UTA",
        "STAT": "FGM",
        "STAT_VALUE": 17,
        "STAT_ORDER": 8,
        "DATE_EST": "2024-01-27T00:00:00"
      },
      {
        "PLAYER_ID": 1629023,
        "GAME_ID": "0022201134",
        "GAME_DATE": "Mar 28 2023",
        "VS_TEAM_ID": 1610612760,
        "VS_TEAM_CITY": "Oklahoma City",
        "VS_TEAM_NAME": "Thunder",
        "VS_TEAM_ABBREVIATION": "OKC",
        "STAT": "FGA",
        "STAT_VALUE": 24,
        "STAT_ORDER": 9,
        "DATE_EST": "2023-03-28T00:00:00"
      },
      {
        "PLAYER_ID": 1629023,
        "GAME_ID": "0022300647",
        "GAME_DATE": "Jan 27 2024",
        "VS_TEAM_ID": 1610612762,
        "VS_TEAM_CITY": "Utah",
        "VS_TEAM_NAME": "Jazz",
        "VS_TEAM_ABBREVIATION": "UTA",
        "STAT": "FG3M",
        "STAT_VALUE": 7,
        "STAT_ORDER": 10,
        "DATE_EST": "2024-01-27T00:00:00"
      },
      {
        "PLAYER_ID": 1629023,
        "GAME_ID": "0021900003",
        "GAME_DATE": "Oct 23 2019",
        "VS_TEAM_ID": 1610612741,
        "VS_TEAM_CITY": "Chicago",
        "VS_TEAM_NAME": "Bulls",
        "VS_TEAM_ABBREVIATION": "CHI",
        "STAT": "FG3M",
        "STAT_VALUE": 7,
        "STAT_ORDER": 10,
        "DATE_EST": "2019-10-23T00:00:00"
      },
      {
        "PLAYER_ID": 1629023,
        "GAME_ID": "0022300017",
        "GAME_DATE": "Nov 14 2023",
        "VS_TEAM_ID": 1610612748,
        "VS_TEAM_CITY": "Miami",
        "VS_TEAM_NAME": "Heat",
        "VS_TEAM_ABBREVIATION": "MIA",
        "STAT": "FG3A",
        "STAT_VALUE": 11,
        "STAT_ORDER": 11,
        "DATE_EST": "2023-11-14T00:00:00"
      },
      {
        "PLAYER_ID": 1629023,
        "GAME_ID": "0022200326",
        "GAME_DATE": "Dec 02 2022",
        "VS_TEAM_ID": 1610612764,
        "VS_TEAM_CITY": "Washington",
        "VS_TEAM_NAME": "Wizards",
        "VS_TEAM_ABBREVIATION": "WAS",
        "STAT": "FG3A",
        "STAT_VALUE": 11,
        "STAT_ORDER": 11,
        "DATE_EST": "2022-12-02T00:00:00"
      },
      {
        "PLAYER_ID": 1629023,
        "GAME_ID": "0022100353",
        "GAME_DATE": "Dec 06 2021",
        "VS_TEAM_ID": 1610612755,
        "VS_TEAM_CITY": "Philadelphia",
        "VS_TEAM_NAME": "76ers",
        "VS_TEAM_ABBREVIATION": "PHI",
        "STAT": "FG3A",
        "STAT_VALUE": 11,
        "STAT_ORDER": 11,
        "DATE_EST": "2021-12-06T00:00:00"
      },
      {
        "PLAYER_ID": 1629023,
        "GAME_ID": "0022000362",
        "GAME_DATE": "Apr 18 2021",
        "VS_TEAM_ID": 1610612757,
        "VS_TEAM_CITY": "Portland",
        "VS_TEAM_NAME": "Trail Blazers",
        "VS_TEAM_ABBREVIATION": "POR",
        "STAT": "FG3A",
        "STAT_VALUE": 11,
        "STAT_ORDER": 11,
        "DATE_EST": "2021-04-18T00:00:00"
      },
      {
        "PLAYER_ID": 1629023,
        "GAME_ID": "0021900003",
        "GAME_DATE": "Oct 23 2019",
        "VS_TEAM_ID": 1610612741,
        "VS_TEAM_CITY": "Chicago",
        "VS_TEAM_NAME": "Bulls",
        "VS_TEAM_ABBREVIATION": "CHI",
        "STAT": "FG3A",
        "STAT_VALUE": 11,
        "STAT_ORDER": 11,
        "DATE_EST": "2019-10-23T00:00:00"
      },
      {
        "PLAYER_ID": 1629023,
        "GAME_ID": "0021900336",
        "GAME_DATE": "Dec 08 2019",
        "VS_TEAM_ID": 1610612737,
        "VS_TEAM_CITY": "Atlanta",
        "VS_TEAM_NAME": "Hawks",
        "VS_TEAM_ABBREVIATION": "ATL",
        "STAT": "FTM",
        "STAT_VALUE": 12,
        "STAT_ORDER": 12,
        "DATE_EST": "2019-12-08T00:00:00"
      },
      {
        "PLAYER_ID": 1629023,
        "GAME_ID": "0021900336",
        "GAME_DATE": "Dec 08 2019",
        "VS_TEAM_ID": 1610612737,
        "VS_TEAM_CITY": "Atlanta",
        "VS_TEAM_NAME": "Hawks",
        "VS_TEAM_ABBREVIATION": "ATL",
        "STAT": "FTA",
        "STAT_VALUE": 13,
        "STAT_ORDER": 13,
        "DATE_EST": "2019-12-08T00:00:00"
      }
    ]
  }
}