{
  "last_updated": "2025-11-05T22:44:31.456717",
  "player_id": 1642843,
  "player_name": "Cooper Flagg",
  "season": "2025-26",
  "data": {
    "SeasonTotalsRegularSeason": [
      {
        "PLAYER_ID": 1642843,
        "SEASON_ID": "2025-26",
        "LEAGUE_ID": "00",
        "TEAM_ID": 1610612742,
        "TEAM_ABBREVIATION": "DAL",
        "PLAYER_AGE": 18.0,
        "GP": 7,
        "GS": 7,
        "MIN": 229,
        "FGM": 33,
        "FGA": 85,
        "FG_PCT": 0.388,
        "FG3M": 8,
        "FG3A": 26,
        "FG3_PCT": 0.308,
        "FTM": 21,
        "FTA": 21,
        "FT_PCT": 1.0,
        "OREB": 7,
        "DREB": 37,
        "REB": 44,
        "AST": 20,
        "STL": 6,
        "BLK": 3,
        "TOV": 15,
        "PF": 20,
        "PTS": 95
      }
    ],
    "CareerTotalsRegularSeason": [
      {
        "PLAYER_ID": 1642843,
        "LEAGUE_ID": "00",
        "TEAM_ID": 0,
        "GP": 7,
        "GS": 7,
        "MIN": 228,
        "FGM": 33,
        "FGA": 85,
        "FG_PCT": 0.388235294117,
        "FG3M": 8,
        "FG3A": 26,
        "FG3_PCT": 0.307692307692,
        "FTM": 21,
        "FTA": 21,
        "FT_PCT": 1.0,
        "OREB": 7,
        "DREB": 37,
        "REB": 44,
        "AST": 20,
        "STL": 6,
        "BLK": 3,
        "TOV": 15,
        "PF": 20,
        "PTS": 95
      }
    ],
    "SeasonTotalsPostSeason": [],
    "CareerTotalsPostSeason": [],
    "SeasonTotalsAllStarSeason": [],
    "CareerTotalsAllStarSeason": [],
    "SeasonTotalsCollegeSeason": [],
    "CareerTotalsCollegeSeason": [],
    "SeasonTotalsShowcaseSeason": [],
    "CareerTotalsShowcaseSeason": [],
    "SeasonRankingsRegularSeason": [
      {
        "PLAYER_ID": 1642843,
        "SEASON_ID": "2025-26",
        "LEAGUE_ID": "00",
        "TEAM_ID": 1610612742,
        "TEAM_ABBREVIATION": "DAL",
        "PLAYER_AGE": "NR",
        "GP": "NR",
        "GS": "NR",
        "RANK_MIN": 35,
        "RANK_FGM": 89,
        "RANK_FGA": 63,
        "RANK_FG_PCT": 140,
        "RANK_FG3M": 145,
        "RANK_FG3A": 123,
        "RANK_FG3_PCT": 143,
        "RANK_FTM": 61,
        "RANK_FTA": 81,
        "RANK_FT_PCT": 1,
        "RANK_OREB": 111,
        "RANK_DREB": 34,
        "RANK_REB": 50,
        "RANK_AST": 94,
        "RANK_STL": 101,
        "RANK_BLK": 92,
        "RANK_TOV": 53,
        "RANK_PTS": 86,
        "RANK_EFF": 105
      }
    ],
    "SeasonRankingsPostSeason": [],
    "SeasonHighs": [
      {
        "PLAYER_ID": 1642843,
        "GAME_ID": "0022500111",
        "GAME_DATE": "Oct 26 2025",
        "VS_TEAM_ID": 1610612761,
        "VS_TEAM_CITY": "Toronto",
        "VS_TEAM_NAME": "Raptors",
        "VS_TEAM_ABBREVIATION": "TOR",
        "STAT": "PTS",
        "STAT_VALUE": 22,
        "STAT_ORDER": 1,
        "DATE_EST": "2025-10-26T00:00:00"
      },
      {
        "PLAYER_ID": 1642843,
        "GAME_ID": "0022500133",
        "GAME_DATE": "Oct 29 2025",
        "VS_TEAM_ID": 1610612754,
        "VS_TEAM_CITY": "Indiana",
        "VS_TEAM_NAME": "Pacers",
        "VS_TEAM_ABBREVIATION": "IND",
        "STAT": "REB",
        "STAT_VALUE": 10,
        "STAT_ORDER": 2,
        "DATE_EST": "2025-10-29T00:00:00"
      },
      {
        "PLAYER_ID": 1642843,
        "GAME_ID": "0022500004",
        "GAME_DATE": "Oct 22 2025",
        "VS_TEAM_ID": 1610612759,
        "VS_TEAM_CITY": "San Antonio",
        "VS_TEAM_NAME": "Spurs",
        "VS_TEAM_ABBREVIATION": "SAS",
        "STAT": "REB",
        "STAT_VALUE": 10,
        "STAT_ORDER": 2,
        "DATE_EST": "2025-10-22T00:00:00"
      },
      {
        "PLAYER_ID": 1642843,
        "GAME_ID": "0022500160",
        "GAME_DATE": "Nov 03 2025",
        "VS_TEAM_ID": 1610612745,
        "VS_TEAM_CITY": "Houston",
        "VS_TEAM_NAME": "Rockets",
        "VS_TEAM_ABBREVIATION": "HOU",
        "STAT": "OREB",
        "STAT_VALUE": 2,
        "STAT_ORDER": 3,
        "DATE_EST": "2025-11-03T00:00:00"
      },
      {
        "PLAYER_ID": 1642843,
        "GAME_ID": "0022500147",
        "GAME_DATE": "Nov 01 2025",
        "VS_TEAM_ID": 1610612765,
        "VS_TEAM_CITY": "Detroit",
        "VS_TEAM_NAME": "Pistons",
        "VS_TEAM_ABBREVIATION": "DET",
        "STAT": "OREB",
        "STAT_VALUE": 2,
        "STAT_ORDER": 3,
        "DATE_EST": "2025-11-01T00:00:00"
      },
      {
        "PLAYER_ID": 1642843,
        "GAME_ID": "0022500133",
        "GAME_DATE": "Oct 29 2025",
        "VS_TEAM_ID": 1610612754,
        "VS_TEAM_CITY": "Indiana",
        "VS_TEAM_NAME": "Pacers",
        "VS_TEAM_ABBREVIATION": "IND",
        "STAT": "DREB",
        "STAT_VALUE": 9,
        "STAT_ORDER": 4,
        "DATE_EST": "2025-10-29T00:00:00"
      },
      {
        "PLAYER_ID": 1642843,
        "GAME_ID": "0022500004",
        "GAME_DATE": "Oct 22 2025",
        "VS_TEAM_ID": 1610612759,
        "VS_TEAM_CITY": "San Antonio",
        "VS_TEAM_NAME": "Spurs",
        "VS_TEAM_ABBREVIATION": "SAS",
        "STAT": "DREB",
        "STAT_VALUE": 9,
        "STAT_ORDER": 4,
        "DATE_EST": "2025-10-22T00:00:00"
      },
      {
        "PLAYER_ID": 1642843,
        "GAME_ID": "0022500096",
        "GAME_DATE": "Oct 24 2025",
        "VS_TEAM_ID": 1610612764,
        "VS_TEAM_CITY": "Washington",
        "VS_TEAM_NAME": "Wizards",
        "VS_TEAM_ABBREVIATION": "WAS",
        "STAT": "AST",
        "STAT_VALUE": 6,
        "STAT_ORDER": 5,
        "DATE_EST": "2025-10-24T00:00:00"
      },
      {
        "PLAYER_ID": 1642843,
        "GAME_ID": "0022500119",
        "GAME_DATE": "Oct 27 2025",
        "VS_TEAM_ID": 1610612760,
        "VS_TEAM_CITY": "Oklahoma City",
        "VS_TEAM_NAME": "Thunder",
        "VS_TEAM_ABBREVIATION": "OKC",
        "STAT": "STL",
        "STAT_VALUE": 2,
        "STAT_ORDER": 6,
        "DATE_EST": "2025-10-27T00:00:00"
      },
      {
        "PLAYER_ID": 1642843,
        "GAME_ID": "0022500133",
        "GAME_DATE": "Oct 29 2025",
        "VS_TEAM_ID": 1610612754,
        "VS_TEAM_CITY": "Indiana",
        "VS_TEAM_NAME": "Pacers",
        "VS_TEAM_ABBREVIATION": "IND",
        "STAT": "BLK",
        "STAT_VALUE": 1,
        "STAT_ORDER": 7,
        "DATE_EST": "2025-10-29T00:00:00"
      },
      {
        "PLAYER_ID": 1642843,
        "GAME_ID": "0022500111",
        "GAME_DATE": "Oct 26 2025",
        "VS_TEAM_ID": 1610612761,
        "VS_TEAM_CITY": "Toronto",
        "VS_TEAM_NAME": "Raptors",
        "VS_TEAM_ABBREVIATION": "TOR",
        "STAT": "BLK",
        "STAT_VALUE": 1,
        "STAT_ORDER": 7,
        "DATE_EST": "2025-10-26T00:00:00"
      },
      {
        "PLAYER_ID": 1642843,
        "GAME_ID": "0022500096",
        "GAME_DATE": "Oct 24 2025",
        "VS_TEAM_ID": 1610612764,
        "VS_TEAM_CITY": "Washington",
        "VS_TEAM_NAME": "Wizards",
        "VS_TEAM_ABBREVIATION": "WAS",
        "STAT": "BLK",
        "STAT_VALUE": 1,
        "STAT_ORDER": 7,
        "DATE_EST": "2025-10-24T00:00:00"
      },
      {
        "PLAYER_ID": 1642843,
        "GAME_ID": "0022500111",
        "GAME_DATE": "Oct 26 2025",
        "VS_TEAM_ID": 1610612761,
        "VS_TEAM_CITY": "Toronto",
        "VS_TEAM_NAME": "Raptors",
        "VS_TEAM_ABBREVIATION": "TOR",
        "STAT": "FGM",
        "STAT_VALUE": 8,
        "STAT_ORDER": 8,
        "DATE_EST": "2025-10-26T00:00:00"
      },
      {
        "PLAYER_ID": 1642843,
        "GAME_ID": "0022500147",
        "GAME_DATE": "Nov 01 2025",
        "VS_TEAM_ID": 1610612765,
        "VS_TEAM_CITY": "Detroit",
        "VS_TEAM_NAME": "Pistons",
        "VS_TEAM_ABBREVIATION": "DET",
        "STAT": "FGA",
        "STAT_VALUE": 14,
        "STAT_ORDER": 9,
        "DATE_EST": "2025-11-01T00:00:00"
      },
      {
        "PLAYER_ID": 1642843,
        "GAME_ID": "0022500111",
        "GAME_DATE": "Oct 26 2025",
        "VS_TEAM_ID": 1610612761,
        "VS_TEAM_CITY": "Toronto",
        "VS_TEAM_NAME": "Raptors",
        "VS_TEAM_ABBREVIATION": "TOR",
        "STAT": "FGA",
        "STAT_VALUE": 14,
        "STAT_ORDER": 9,
        "DATE_EST": "2025-10-26T00:00:00"
      },
      {
        "PLAYER_ID": 1642843,
        "GAME_ID": "0022500096",
        "GAME_DATE": "Oct 24 2025",
        "VS_TEAM_ID": 1610612764,
        "VS_TEAM_CITY": "Washington",
        "VS_TEAM_NAME": "Wizards",
        "VS_TEAM_ABBREVIATION": "WAS",
        "STAT": "FGA",
        "STAT_VALUE": 14,
        "STAT_ORDER": 9,
        "DATE_EST": "2025-10-24T00:00:00"
      },
      {
        "PLAYER_ID": 1642843,
        "GAME_ID": "0022500160",
        "GAME_DATE": "Nov 03 2025",
        "VS_TEAM_ID": 1610612745,
        "VS_TEAM_CITY": "Houston",
        "VS_TEAM_NAME": "Rockets",
        "VS_TEAM_ABBREVIATION": "HOU",
        "STAT": "FG3M",
        "STAT_VALUE": 2,
        "STAT_ORDER": 10,
        "DATE_EST": "2025-11-03T00:00:00"
      },
      {
        "PLAYER_ID": 1642843,
        "GAME_ID": "0022500147",
        "GAME_DATE": "Nov 01 2025",
        "VS_TEAM_ID": 1610612765,
        "VS_TEAM_CITY": "Detroit",
        "VS_TEAM_NAME": "Pistons",
        "VS_TEAM_ABBREVIATION": "DET",
        "STAT": "FG3M",
        "STAT_VALUE": 2,
        "STAT_ORDER": 10,
        "DATE_EST": "2025-11-01T00:00:00"
      },
      {
        "PLAYER_ID": 1642843,
        "GAME_ID": "0022500111",
        "GAME_DATE": "Oct 26 2025",
        "VS_TEAM_ID": 1610612761,
        "VS_TEAM_CITY": "Toronto",
        "VS_TEAM_NAME": "Raptors",
        "VS_TEAM_ABBREVIATION": "TOR",
        "STAT": "FG3M",
        "STAT_VALUE": 2,
        "STAT_ORDER": 10,
        "DATE_EST": "2025-10-26T00:00:00"
      },
      {
        "PLAYER_ID": 1642843,
        "GAME_ID": "0022500096",
        "GAME_DATE": "Oct 24 2025",
        "VS_TEAM_ID": 1610612764,
        "VS_TEAM_CITY": "Washington",
        "VS_TEAM_NAME": "Wizards",
        "VS_TEAM_ABBREVIATION": "WAS",
        "STAT": "FG3M",
        "STAT_VALUE": 2,
        "STAT_ORDER": 10,
        "DATE_EST": "2025-10-24T00:00:00"
      },
      {
        "PLAYER_ID": 1642843,
        "GAME_ID": "0022500147",
        "GAME_DATE": "Nov 01 2025",
        "VS_TEAM_ID": 1610612765,
        "VS_TEAM_CITY": "Detroit",
        "VS_TEAM_NAME": "Pistons",
        "VS_TEAM_ABBREVIATION": "DET",
        "STAT": "FG3A",
        "STAT_VALUE": 6,
        "STAT_ORDER": 11,
        "DATE_EST": "2025-11-01T00:00:00"
      },
      {
        "PLAYER_ID": 1642843,
        "GAME_ID": "0022500111",
        "GAME_DATE": "Oct 26 2025",
        "VS_TEAM_ID": 1610612761,
        "VS_TEAM_CITY": "Toronto",
        "VS_TEAM_NAME": "Raptors",
        "VS_TEAM_ABBREVIATION": "TOR",
        "STAT": "FG3A",
        "STAT_VALUE": 6,
        "STAT_ORDER": 11,
        "DATE_EST": "2025-10-26T00:00:00"
      },
      {
        "PLAYER_ID": 1642843,
        "GAME_ID": "0022500147",
        "GAME_DATE": "Nov 01 2025",
        "VS_TEAM_ID": 1610612765,
        "VS_TEAM_CITY": "Detroit",
        "VS_TEAM_NAME": "Pistons",
        "VS_TEAM_ABBREVIATION": "DET",
        "STAT": "FTM",
        "STAT_VALUE": 8,
        "STAT_ORDER": 12,
        "DATE_EST": "2025-11-01T00:00:00"
      },
      {
        "PLAYER_ID": 1642843,
        "GAME_ID": "0022500147",
        "GAME_DATE": "Nov 01 2025",
        "VS_TEAM_ID": 1610612765,
        "VS_TEAM_CITY": "Detroit",
        "VS_TEAM_NAME": "Pistons",
        "VS_TEAM_ABBREVIATION": "DET",
        "STAT": "FTA",
        "STAT_VALUE": 8,
        "STAT_ORDER": 13,
        "DATE_EST": "2025-11-01T00:00:00"
      }
    ],
    "CareerHighs": [
      {
        "PLAYER_ID": 1642843,
        "GAME_ID": "0022500111",
        "GAME_DATE": "Oct 26 2025",
        "VS_TEAM_ID": 1610612761,
        "VS_TEAM_CITY": "Toronto",
        "VS_TEAM_NAME": "Raptors",
        "VS_TEAM_ABBREVIATION": "TOR",
        "STAT": "PTS",
        "STAT_VALUE": 22,
        "STAT_ORDER": 1,
        "DATE_EST": "2025-10-26T00:00:00"
      },
      {
        "PLAYER_ID": 1642843,
        "GAME_ID": "0022500133",
        "GAME_DATE": "Oct 29 2025",
        "VS_TEAM_ID": 1610612754,
        "VS_TEAM_CITY": "Indiana",
        "VS_TEAM_NAME": "Pacers",
        "VS_TEAM_ABBREVIATION": "IND",
        "STAT": "REB",
        "STAT_VALUE": 10,
        "STAT_ORDER": 2,
        "DATE_EST": "2025-10-29T00:00:00"
      },
      {
        "PLAYER_ID": 1642843,
        "GAME_ID": "0022500004",
        "GAME_DATE": "Oct 22 2025",
        "VS_TEAM_ID": 1610612759,
        "VS_TEAM_CITY": "San Antonio",
        "VS_TEAM_NAME": "Spurs",
        "VS_TEAM_ABBREVIATION": "SAS",
        "STAT": "REB",
        "STAT_VALUE": 10,
        "STAT_ORDER": 2,
        "DATE_EST": "2025-10-22T00:00:00"
      },
      {
        "PLAYER_ID": 1642843,
        "GAME_ID": "0022500160",
        "GAME_DATE": "Nov 03 2025",
        "VS_TEAM_ID": 1610612745,
        "VS_TEAM_CITY": "Houston",
        "VS_TEAM_NAME": "Rockets",
        "VS_TEAM_ABBREVIATION": "HOU",
        "STAT": "OREB",
        "STAT_VALUE": 2,
        "STAT_ORDER": 3,
        "DATE_EST": "2025-11-03T00:00:00"
      },
      {
        "PLAYER_ID": 1642843,
        "GAME_ID": "0022500147",
        "GAME_DATE": "Nov 01 2025",
        "VS_TEAM_ID": 1610612765,
        "VS_TEAM_CITY": "Detroit",
        "VS_TEAM_NAME": "Pistons",
        "VS_TEAM_ABBREVIATION": "DET",
        "STAT": "OREB",
        "STAT_VALUE": 2,
        "STAT_ORDER": 3,
        "DATE_EST": "2025-11-01T00:00:00"
      },
      {
        "PLAYER_ID": 1642843,
        "GAME_ID": "0022500133",
        "GAME_DATE": "Oct 29 2025",
        "VS_TEAM_ID": 1610612754,
        "VS_TEAM_CITY": "Indiana",
        "VS_TEAM_NAME": "Pacers",
        "VS_TEAM_ABBREVIATION": "IND",
        "STAT": "DREB",
        "STAT_VALUE": 9,
        "STAT_ORDER": 4,
        "DATE_EST": "2025-10-29T00:00:00"
      },
      {
        "PLAYER_ID": 1642843,
        "GAME_ID": "0022500004",
        "GAME_DATE": "Oct 22 2025",
        "VS_TEAM_ID": 1610612759,
        "VS_TEAM_CITY": "San Antonio",
        "VS_TEAM_NAME": "Spurs",
        "VS_TEAM_ABBREVIATION": "SAS",
        "STAT": "DREB",
        "STAT_VALUE": 9,
        "STAT_ORDER": 4,
        "DATE_EST": "2025-10-22T00:00:00"
      },
      {
        "PLAYER_ID": 1642843,
        "GAME_ID": "0022500096",
        "GAME_DATE": "Oct 24 2025",
        "VS_TEAM_ID": 1610612764,
        "VS_TEAM_CITY": "Washington",
        "VS_TEAM_NAME": "Wizards",
        "VS_TEAM_ABBREVIATION": "WAS",
        "STAT": "AST",
        "STAT_VALUE": 6,
        "STAT_ORDER": 5,
        "DATE_EST": "2025-10-24T00:00:00"
      },
      {
        "PLAYER_ID": 1642843,
        "GAME_ID": "0022500119",
        "GAME_DATE": "Oct 27 2025",
        "VS_TEAM_ID": 1610612760,
        "VS_TEAM_CITY": "Oklahoma City",
        "VS_TEAM_NAME": "Thunder",
        "VS_TEAM_ABBREVIATION": "OKC",
        "STAT": "STL",
        "STAT_VALUE": 2,
        "STAT_ORDER": 6,
        "DATE_EST": "2025-10-27T00:00:00"
      },
      {
        "PLAYER_ID": 1642843,
        "GAME_ID": "0022500133",
        "GAME_DATE": "Oct 29 2025",
        "VS_TEAM_ID": 1610612754,
        "VS_TEAM_CITY": "Indiana",
        "VS_TEAM_NAME": "Pacers",
        "VS_TEAM_ABBREVIATION": "IND",
        "STAT": "BLK",
        "STAT_VALUE": 1,
        "STAT_ORDER": 7,
        "DATE_EST": "2025-10-29T00:00:00"
      },
      {
        "PLAYER_ID": 1642843,
        "GAME_ID": "0022500111",
        "GAME_DATE": "Oct 26 2025",
        "VS_TEAM_ID": 1610612761,
        "VS_TEAM_CITY": "Toronto",
        "VS_TEAM_NAME": "Raptors",
        "VS_TEAM_ABBREVIATION": "TOR",
        "STAT": "BLK",
        "STAT_VALUE": 1,
        "STAT_ORDER": 7,
        "DATE_EST": "2025-10-26T00:00:00"
      },
      {
        "PLAYER_ID": 1642843,
        "GAME_ID": "0022500096",
        "GAME_DATE": "Oct 24 2025",
        "VS_TEAM_ID": 1610612764,
        "VS_TEAM_CITY": "Washington",
        "VS_TEAM_NAME": "Wizards",
        "VS_TEAM_ABBREVIATION": "WAS",
        "STAT": "BLK",
        "STAT_VALUE": 1,
        "STAT_ORDER": 7,
        "DATE_EST": "2025-10-24T00:00:00"
      },
      {
        "PLAYER_ID": 1642843,
        "GAME_ID": "0022500111",
        "GAME_DATE": "Oct 26 2025",
        "VS_TEAM_ID": 1610612761,
        "VS_TEAM_CITY": "Toronto",
        "VS_TEAM_NAME": "Raptors",
        "VS_TEAM_ABBREVIATION": "TOR",
        "STAT": "FGM",
        "STAT_VALUE": 8,
        "STAT_ORDER": 8,
        "DATE_EST": "2025-10-26T00:00:00"
      },
      {
        "PLAYER_ID": 1642843,
        "GAME_ID": "0022500147",
        "GAME_DATE": "Nov 01 2025",
        "VS_TEAM_ID": 1610612765,
        "VS_TEAM_CITY": "Detroit",
        "VS_TEAM_NAME": "Pistons",
        "VS_TEAM_ABBREVIATION": "DET",
        "STAT": "FGA",
        "STAT_VALUE": 14,
        "STAT_ORDER": 9,
        "DATE_EST": "2025-11-01T00:00:00"
      },
      {
        "PLAYER_ID": 1642843,
        "GAME_ID": "0022500111",
        "GAME_DATE": "Oct 26 2025",
        "VS_TEAM_ID": 1610612761,
        "VS_TEAM_CITY": "Toronto",
        "VS_TEAM_NAME": "Raptors",
        "VS_TEAM_ABBREVIATION": "TOR",
        "STAT": "FGA",
        "STAT_VALUE": 14,
        "STAT_ORDER": 9,
        "DATE_EST": "2025-10-26T00:00:00"
      },
      {
        "PLAYER_ID": 1642843,
        "GAME_ID": "0022500096",
        "GAME_DATE": "Oct 24 2025",
        "VS_TEAM_ID": 1610612764,
        "VS_TEAM_CITY": "Washington",
        "VS_TEAM_NAME": "Wizards",
        "VS_TEAM_ABBREVIATION": "WAS",
        "STAT": "FGA",
        "STAT_VALUE": 14,
        "STAT_ORDER": 9,
        "DATE_EST": "2025-10-24T00:00:00"
      },
      {
        "PLAYER_ID": 1642843,
        "GAME_ID": "0022500160",
        "GAME_DATE": "Nov 03 2025",
        "VS_TEAM_ID": 1610612745,
        "VS_TEAM_CITY": "Houston",
        "VS_TEAM_NAME": "Rockets",
        "VS_TEAM_ABBREVIATION": "HOU",
        "STAT": "FG3M",
        "STAT_VALUE": 2,
        "STAT_ORDER": 10,
        "DATE_EST": "2025-11-03T00:00:00"
      },
      {
        "PLAYER_ID": 1642843,
        "GAME_ID": "0022500147",
        "GAME_DATE": "Nov 01 2025",
        "VS_TEAM_ID": 1610612765,
        "VS_TEAM_CITY": "Detroit",
        "VS_TEAM_NAME": "Pistons",
        "VS_TEAM_ABBREVIATION": "DET",
        "STAT": "FG3M",
        "STAT_VALUE": 2,
        "STAT_ORDER": 10,
        "DATE_EST": "2025-11-01T00:00:00"
      },
      {
        "PLAYER_ID": 1642843,
        "GAME_ID": "0022500111",
        "GAME_DATE": "Oct 26 2025",
        "VS_TEAM_ID": 1610612761,
        "VS_TEAM_CITY": "Toronto",
        "VS_TEAM_NAME": "Raptors",
        "VS_TEAM_ABBREVIATION": "TOR",
        "STAT": "FG3M",
        "STAT_VALUE": 2,
        "STAT_ORDER": 10,
        "DATE_EST": "2025-10-26T00:00:00"
      },
      {
        "PLAYER_ID": 1642843,
        "GAME_ID": "0022500096",
        "GAME_DATE": "Oct 24 2025",
        "VS_TEAM_ID": 1610612764,
        "VS_TEAM_CITY": "Washington",
        "VS_TEAM_NAME": "Wizards",
        "VS_TEAM_ABBREVIATION": "WAS",
        "STAT": "FG3M",
        "STAT_VALUE": 2,
        "STAT_ORDER": 10,
        "DATE_EST": "2025-10-24T00:00:00"
      },
      {
        "PLAYER_ID": 1642843,
        "GAME_ID": "0022500147",
        "GAME_DATE": "Nov 01 2025",
        "VS_TEAM_ID": 1610612765,
        "VS_TEAM_CITY": "Detroit",
        "VS_TEAM_NAME": "Pistons",
        "VS_TEAM_ABBREVIATION": "DET",
        "STAT": "FG3A",
        "STAT_VALUE": 6,
        "STAT_ORDER": 11,
        "DATE_EST": "2025-11-01T00:00:00"
      },
      {
        "PLAYER_ID": 1642843,
        "GAME_ID": "0022500111",
        "GAME_DATE": "Oct 26 2025",
        "VS_TEAM_ID": 1610612761,
        "VS_TEAM_CITY": "Toronto",
        "VS_TEAM_NAME": "Raptors",
        "VS_TEAM_ABBREVIATION": "TOR",
        "STAT": "FG3A",
        "STAT_VALUE": 6,
        "STAT_ORDER": 11,
        "DATE_EST": "2025-10-26T00:00:00"
      },
      {
        "PLAYER_ID": 1642843,
        "GAME_ID": "0022500147",
        "GAME_DATE": "Nov 01 2025",
        "VS_TEAM_ID": 1610612765,
        "VS_TEAM_CITY": "Detroit",
        "VS_TEAM_NAME": "Pistons",
        "VS_TEAM_ABBREVIATION": "DET",
        "STAT": "FTM",
        "STAT_VALUE": 8,
        "STAT_ORDER": 12,
        "DATE_EST": "2025-11-01T00:00:00"
      },
      {
        "PLAYER_ID": 1642843,
        "GAME_ID": "0022500147",
        "GAME_DATE": "Nov 01 2025",
        "VS_TEAM_ID": 1610612765,
        "VS_TEAM_CITY": "Detroit",
        "VS_TEAM_NAME": "Pistons",
        "VS_TEAM_ABBREVIATION": "DET",
        "STAT": "FTA",
        "STAT_VALUE": 8,
        "STAT_ORDER": 13,
        "DATE_EST": "2025-11-01T00:00:00"
      }
    ]
  }
}