{
  "last_updated": "2025-11-07T20:58:01.365249",
  "player_id": 1642368,
  "player_name": "N'Faly Dante",
  "season": "2025-26",
  "data": {
    "SeasonTotalsRegularSeason": [
      {
        "PLAYER_ID": 1642368,
        "SEASON_ID": "2024-25",
        "LEAGUE_ID": "00",
        "TEAM_ID": 1610612745,
        "TEAM_ABBREVIATION": "HOU",
        "PLAYER_AGE": 23.0,
        "GP": 4,
        "GS": 0,
        "MIN": 51,
        "FGM": 10,
        "FGA": 13,
        "FG_PCT": 0.769,
        "FG3M": 0,
        "FG3A": 0,
        "FG3_PCT": 0.0,
        "FTM": 4,
        "FTA": 5,
        "FT_PCT": 0.8,
        "OREB": 6,
        "DREB": 15,
        "REB": 21,
        "AST": 2,
        "STL": 1,
        "BLK": 5,
        "TOV": 2,
        "PF": 9,
        "PTS": 24
      },
      {
        "PLAYER_ID": 1642368,
        "SEASON_ID": "2025-26",
        "LEAGUE_ID": "00",
        "TEAM_ID": 1610612737,
        "TEAM_ABBREVIATION": "ATL",
        "PLAYER_AGE": 24.0,
        "GP": 3,
        "GS": 0,
        "MIN": 14,
        "FGM": 1,
        "FGA": 4,
        "FG_PCT": 0.25,
        "FG3M": 0,
        "FG3A": 0,
        "FG3_PCT": 0.0,
        "FTM": 1,
        "FTA": 1,
        "FT_PCT": 1.0,
        "OREB": 3,
        "DREB": 4,
        "REB": 7,
        "AST": 0,
        "STL": 2,
        "BLK": 0,
        "TOV": 1,
        "PF": 1,
        "PTS": 3
      }
    ],
    "CareerTotalsRegularSeason": [
      {
        "PLAYER_ID": 1642368,
        "LEAGUE_ID": "00",
        "TEAM_ID": 0,
        "GP": 7,
        "GS": 0,
        "MIN": 64,
        "FGM": 11,
        "FGA": 17,
        "FG_PCT": 0.647058823529,
        "FG3M": 0,
        "FG3A": 0,
        "FG3_PCT": 0.0,
        "FTM": 5,
        "FTA": 6,
        "FT_PCT": 0.833333333333,
        "OREB": 9,
        "DREB": 19,
        "REB": 28,
        "AST": 2,
        "STL": 3,
        "BLK": 5,
        "TOV": 3,
        "PF": 10,
        "PTS": 27
      }
    ],
    "SeasonTotalsPostSeason": [],
    "CareerTotalsPostSeason": [],
    "SeasonTotalsAllStarSeason": [],
    "CareerTotalsAllStarSeason": [],
    "SeasonTotalsCollegeSeason": [],
    "CareerTotalsCollegeSeason": [],
    "SeasonTotalsShowcaseSeason": [],
    "CareerTotalsShowcaseSeason": [],
    "SeasonRankingsRegularSeason": [
      {
        "PLAYER_ID": 1642368,
        "SEASON_ID": "2024-25",
        "LEAGUE_ID": "00",
        "TEAM_ID": 1610612745,
        "TEAM_ABBREVIATION": "HOU",
        "PLAYER_AGE": "NR",
        "GP": "NR",
        "GS": "NR",
        "RANK_MIN": 523,
        "RANK_FGM": 504,
        "RANK_FGA": 526,
        "RANK_FG_PCT": null,
        "RANK_FG3M": 499,
        "RANK_FG3A": 542,
        "RANK_FG3_PCT": null,
        "RANK_FTM": 485,
        "RANK_FTA": 498,
        "RANK_FT_PCT": null,
        "RANK_OREB": 468,
        "RANK_DREB": 480,
        "RANK_REB": 478,
        "RANK_AST": 530,
        "RANK_STL": 521,
        "RANK_BLK": 396,
        "RANK_TOV": 520,
        "RANK_PTS": 507,
        "RANK_EFF": 485
      },
      {
        "PLAYER_ID": 1642368,
        "SEASON_ID": "2025-26",
        "LEAGUE_ID": "00",
        "TEAM_ID": 1610612737,
        "TEAM_ABBREVIATION": "ATL",
        "PLAYER_AGE": "NR",
        "GP": "NR",
        "GS": "NR",
        "RANK_MIN": 359,
        "RANK_FGM": 349,
        "RANK_FGA": 347,
        "RANK_FG_PCT": null,
        "RANK_FG3M": 305,
        "RANK_FG3A": 354,
        "RANK_FG3_PCT": null,
        "RANK_FTM": 298,
        "RANK_FTA": 322,
        "RANK_FT_PCT": null,
        "RANK_OREB": 182,
        "RANK_DREB": 284,
        "RANK_REB": 273,
        "RANK_AST": 367,
        "RANK_STL": 207,
        "RANK_BLK": 255,
        "RANK_TOV": 310,
        "RANK_PTS": 360,
        "RANK_EFF": 328
      }
    ],
    "SeasonRankingsPostSeason": [],
    "SeasonHighs": [
      {
        "PLAYER_ID": 1642368,
        "GAME_ID": "0022500020",
        "GAME_DATE": "Oct 31 2025",
        "VS_TEAM_ID": 1610612754,
        "VS_TEAM_CITY": "Indiana",
        "VS_TEAM_NAME": "Pacers",
        "VS_TEAM_ABBREVIATION": "IND",
        "STAT": "PTS",
        "STAT_VALUE": 2,
        "STAT_ORDER": 1,
        "DATE_EST": "2025-10-31T00:00:00"
      },
      {
        "PLAYER_ID": 1642368,
        "GAME_ID": "0022500101",
        "GAME_DATE": "Oct 25 2025",
        "VS_TEAM_ID": 1610612760,
        "VS_TEAM_CITY": "Oklahoma City",
        "VS_TEAM_NAME": "Thunder",
        "VS_TEAM_ABBREVIATION": "OKC",
        "STAT": "REB",
        "STAT_VALUE": 4,
        "STAT_ORDER": 2,
        "DATE_EST": "2025-10-25T00:00:00"
      },
      {
        "PLAYER_ID": 1642368,
        "GAME_ID": "0022500101",
        "GAME_DATE": "Oct 25 2025",
        "VS_TEAM_ID": 1610612760,
        "VS_TEAM_CITY": "Oklahoma City",
        "VS_TEAM_NAME": "Thunder",
        "VS_TEAM_ABBREVIATION": "OKC",
        "STAT": "OREB",
        "STAT_VALUE": 2,
        "STAT_ORDER": 3,
        "DATE_EST": "2025-10-25T00:00:00"
      },
      {
        "PLAYER_ID": 1642368,
        "GAME_ID": "0022500101",
        "GAME_DATE": "Oct 25 2025",
        "VS_TEAM_ID": 1610612760,
        "VS_TEAM_CITY": "Oklahoma City",
        "VS_TEAM_NAME": "Thunder",
        "VS_TEAM_ABBREVIATION": "OKC",
        "STAT": "DREB",
        "STAT_VALUE": 2,
        "STAT_ORDER": 4,
        "DATE_EST": "2025-10-25T00:00:00"
      },
      {
        "PLAYER_ID": 1642368,
        "GAME_ID": "0022500090",
        "GAME_DATE": "Oct 24 2025",
        "VS_TEAM_ID": 1610612753,
        "VS_TEAM_CITY": "Orlando",
        "VS_TEAM_NAME": "Magic",
        "VS_TEAM_ABBREVIATION": "ORL",
        "STAT": "DREB",
        "STAT_VALUE": 2,
        "STAT_ORDER": 4,
        "DATE_EST": "2025-10-24T00:00:00"
      },
      {
        "PLAYER_ID": 1642368,
        "GAME_ID": "0022500020",
        "GAME_DATE": "Oct 31 2025",
        "VS_TEAM_ID": 1610612754,
        "VS_TEAM_CITY": "Indiana",
        "VS_TEAM_NAME": "Pacers",
        "VS_TEAM_ABBREVIATION": "IND",
        "STAT": "AST",
        "STAT_VALUE": 0,
        "STAT_ORDER": 5,
        "DATE_EST": "2025-10-31T00:00:00"
      },
      {
        "PLAYER_ID": 1642368,
        "GAME_ID": "0022500101",
        "GAME_DATE": "Oct 25 2025",
        "VS_TEAM_ID": 1610612760,
        "VS_TEAM_CITY": "Oklahoma City",
        "VS_TEAM_NAME": "Thunder",
        "VS_TEAM_ABBREVIATION": "OKC",
        "STAT": "AST",
        "STAT_VALUE": 0,
        "STAT_ORDER": 5,
        "DATE_EST": "2025-10-25T00:00:00"
      },
      {
        "PLAYER_ID": 1642368,
        "GAME_ID": "0022500090",
        "GAME_DATE": "Oct 24 2025",
        "VS_TEAM_ID": 1610612753,
        "VS_TEAM_CITY": "Orlando",
        "VS_TEAM_NAME": "Magic",
        "VS_TEAM_ABBREVIATION": "ORL",
        "STAT": "AST",
        "STAT_VALUE": 0,
        "STAT_ORDER": 5,
        "DATE_EST": "2025-10-24T00:00:00"
      },
      {
        "PLAYER_ID": 1642368,
        "GAME_ID": "0022500020",
        "GAME_DATE": "Oct 31 2025",
        "VS_TEAM_ID": 1610612754,
        "VS_TEAM_CITY": "Indiana",
        "VS_TEAM_NAME": "Pacers",
        "VS_TEAM_ABBREVIATION": "IND",
        "STAT": "STL",
        "STAT_VALUE": 1,
        "STAT_ORDER": 6,
        "DATE_EST": "2025-10-31T00:00:00"
      },
      {
        "PLAYER_ID": 1642368,
        "GAME_ID": "0022500101",
        "GAME_DATE": "Oct 25 2025",
        "VS_TEAM_ID": 1610612760,
        "VS_TEAM_CITY": "Oklahoma City",
        "VS_TEAM_NAME": "Thunder",
        "VS_TEAM_ABBREVIATION": "OKC",
        "STAT": "STL",
        "STAT_VALUE": 1,
        "STAT_ORDER": 6,
        "DATE_EST": "2025-10-25T00:00:00"
      },
      {
        "PLAYER_ID": 1642368,
        "GAME_ID": "0022500020",
        "GAME_DATE": "Oct 31 2025",
        "VS_TEAM_ID": 1610612754,
        "VS_TEAM_CITY": "Indiana",
        "VS_TEAM_NAME": "Pacers",
        "VS_TEAM_ABBREVIATION": "IND",
        "STAT": "BLK",
        "STAT_VALUE": 0,
        "STAT_ORDER": 7,
        "DATE_EST": "2025-10-31T00:00:00"
      },
      {
        "PLAYER_ID": 1642368,
        "GAME_ID": "0022500101",
        "GAME_DATE": "Oct 25 2025",
        "VS_TEAM_ID": 1610612760,
        "VS_TEAM_CITY": "Oklahoma City",
        "VS_TEAM_NAME": "Thunder",
        "VS_TEAM_ABBREVIATION": "OKC",
        "STAT": "BLK",
        "STAT_VALUE": 0,
        "STAT_ORDER": 7,
        "DATE_EST": "2025-10-25T00:00:00"
      },
      {
        "PLAYER_ID": 1642368,
        "GAME_ID": "0022500090",
        "GAME_DATE": "Oct 24 2025",
        "VS_TEAM_ID": 1610612753,
        "VS_TEAM_CITY": "Orlando",
        "VS_TEAM_NAME": "Magic",
        "VS_TEAM_ABBREVIATION": "ORL",
        "STAT": "BLK",
        "STAT_VALUE": 0,
        "STAT_ORDER": 7,
        "DATE_EST": "2025-10-24T00:00:00"
      },
      {
        "PLAYER_ID": 1642368,
        "GAME_ID": "0022500020",
        "GAME_DATE": "Oct 31 2025",
        "VS_TEAM_ID": 1610612754,
        "VS_TEAM_CITY": "Indiana",
        "VS_TEAM_NAME": "Pacers",
        "VS_TEAM_ABBREVIATION": "IND",
        "STAT": "FGM",
        "STAT_VALUE": 1,
        "STAT_ORDER": 8,
        "DATE_EST": "2025-10-31T00:00:00"
      },
      {
        "PLAYER_ID": 1642368,
        "GAME_ID": "0022500101",
        "GAME_DATE": "Oct 25 2025",
        "VS_TEAM_ID": 1610612760,
        "VS_TEAM_CITY": "Oklahoma City",
        "VS_TEAM_NAME": "Thunder",
        "VS_TEAM_ABBREVIATION": "OKC",
        "STAT": "FGA",
        "STAT_VALUE": 3,
        "STAT_ORDER": 9,
        "DATE_EST": "2025-10-25T00:00:00"
      },
      {
        "PLAYER_ID": 1642368,
        "GAME_ID": "0022500020",
        "GAME_DATE": "Oct 31 2025",
        "VS_TEAM_ID": 1610612754,
        "VS_TEAM_CITY": "Indiana",
        "VS_TEAM_NAME": "Pacers",
        "VS_TEAM_ABBREVIATION": "IND",
        "STAT": "FG3M",
        "STAT_VALUE": 0,
        "STAT_ORDER": 10,
        "DATE_EST": "2025-10-31T00:00:00"
      },
      {
        "PLAYER_ID": 1642368,
        "GAME_ID": "0022500101",
        "GAME_DATE": "Oct 25 2025",
        "VS_TEAM_ID": 1610612760,
        "VS_TEAM_CITY": "Oklahoma City",
        "VS_TEAM_NAME": "Thunder",
        "VS_TEAM_ABBREVIATION": "OKC",
        "STAT": "FG3M",
        "STAT_VALUE": 0,
        "STAT_ORDER": 10,
        "DATE_EST": "2025-10-25T00:00:00"
      },
      {
        "PLAYER_ID": 1642368,
        "GAME_ID": "0022500090",
        "GAME_DATE": "Oct 24 2025",
        "VS_TEAM_ID": 1610612753,
        "VS_TEAM_CITY": "Orlando",
        "VS_TEAM_NAME": "Magic",
        "VS_TEAM_ABBREVIATION": "ORL",
        "STAT": "FG3M",
        "STAT_VALUE": 0,
        "STAT_ORDER": 10,
        "DATE_EST": "2025-10-24T00:00:00"
      },
      {
        "PLAYER_ID": 1642368,
        "GAME_ID": "0022500020",
        "GAME_DATE": "Oct 31 2025",
        "VS_TEAM_ID": 1610612754,
        "VS_TEAM_CITY": "Indiana",
        "VS_TEAM_NAME": "Pacers",
        "VS_TEAM_ABBREVIATION": "IND",
        "STAT": "FG3A",
        "STAT_VALUE": 0,
        "STAT_ORDER": 11,
        "DATE_EST": "2025-10-31T00:00:00"
      },
      {
        "PLAYER_ID": 1642368,
        "GAME_ID": "0022500101",
        "GAME_DATE": "Oct 25 2025",
        "VS_TEAM_ID": 1610612760,
        "VS_TEAM_CITY": "Oklahoma City",
        "VS_TEAM_NAME": "Thunder",
        "VS_TEAM_ABBREVIATION": "OKC",
        "STAT": "FG3A",
        "STAT_VALUE": 0,
        "STAT_ORDER": 11,
        "DATE_EST": "2025-10-25T00:00:00"
      },
      {
        "PLAYER_ID": 1642368,
        "GAME_ID": "0022500090",
        "GAME_DATE": "Oct 24 2025",
        "VS_TEAM_ID": 1610612753,
        "VS_TEAM_CITY": "Orlando",
        "VS_TEAM_NAME": "Magic",
        "VS_TEAM_ABBREVIATION": "ORL",
        "STAT": "FG3A",
        "STAT_VALUE": 0,
        "STAT_ORDER": 11,
        "DATE_EST": "2025-10-24T00:00:00"
      },
      {
        "PLAYER_ID": 1642368,
        "GAME_ID": "0022500101",
        "GAME_DATE": "Oct 25 2025",
        "VS_TEAM_ID": 1610612760,
        "VS_TEAM_CITY": "Oklahoma City",
        "VS_TEAM_NAME": "Thunder",
        "VS_TEAM_ABBREVIATION": "OKC",
        "STAT": "FTM",
        "STAT_VALUE": 1,
        "STAT_ORDER": 12,
        "DATE_EST": "2025-10-25T00:00:00"
      },
      {
        "PLAYER_ID": 1642368,
        "GAME_ID": "0022500101",
        "GAME_DATE": "Oct 25 2025",
        "VS_TEAM_ID": 1610612760,
        "VS_TEAM_CITY": "Oklahoma City",
        "VS_TEAM_NAME": "Thunder",
        "VS_TEAM_ABBREVIATION": "OKC",
        "STAT": "FTA",
        "STAT_VALUE": 1,
        "STAT_ORDER": 13,
        "DATE_EST": "2025-10-25T00:00:00"
      }
    ],
    "CareerHighs": [
      {
        "PLAYER_ID": 1642368,
        "GAME_ID": "0022400879",
        "GAME_DATE": "Mar 03 2025",
        "VS_TEAM_ID": 1610612760,
        "VS_TEAM_CITY": "Oklahoma City",
        "VS_TEAM_NAME": "Thunder",
        "VS_TEAM_ABBREVIATION": "OKC",
        "STAT": "PTS",
        "STAT_VALUE": 10,
        "STAT_ORDER": 1,
        "DATE_EST": "2025-03-03T00:00:00"
      },
      {
        "PLAYER_ID": 1642368,
        "GAME_ID": "0022400879",
        "GAME_DATE": "Mar 03 2025",
        "VS_TEAM_ID": 1610612760,
        "VS_TEAM_CITY": "Oklahoma City",
        "VS_TEAM_NAME": "Thunder",
        "VS_TEAM_ABBREVIATION": "OKC",
        "STAT": "REB",
        "STAT_VALUE": 9,
        "STAT_ORDER": 2,
        "DATE_EST": "2025-03-03T00:00:00"
      },
      {
        "PLAYER_ID": 1642368,
        "GAME_ID": "0022400879",
        "GAME_DATE": "Mar 03 2025",
        "VS_TEAM_ID": 1610612760,
        "VS_TEAM_CITY": "Oklahoma City",
        "VS_TEAM_NAME": "Thunder",
        "VS_TEAM_ABBREVIATION": "OKC",
        "STAT": "OREB",
        "STAT_VALUE": 4,
        "STAT_ORDER": 3,
        "DATE_EST": "2025-03-03T00:00:00"
      },
      {
        "PLAYER_ID": 1642368,
        "GAME_ID": "0022400879",
        "GAME_DATE": "Mar 03 2025",
        "VS_TEAM_ID": 1610612760,
        "VS_TEAM_CITY": "Oklahoma City",
        "VS_TEAM_NAME": "Thunder",
        "VS_TEAM_ABBREVIATION": "OKC",
        "STAT": "DREB",
        "STAT_VALUE": 5,
        "STAT_ORDER": 4,
        "DATE_EST": "2025-03-03T00:00:00"
      },
      {
        "PLAYER_ID": 1642368,
        "GAME_ID": "0022401185",
        "GAME_DATE": "Apr 11 2025",
        "VS_TEAM_ID": 1610612747,
        "VS_TEAM_CITY": "Los Angeles",
        "VS_TEAM_NAME": "Lakers",
        "VS_TEAM_ABBREVIATION": "LAL",
        "STAT": "AST",
        "STAT_VALUE": 1,
        "STAT_ORDER": 5,
        "DATE_EST": "2025-04-11T00:00:00"
      },
      {
        "PLAYER_ID": 1642368,
        "GAME_ID": "0022400879",
        "GAME_DATE": "Mar 03 2025",
        "VS_TEAM_ID": 1610612760,
        "VS_TEAM_CITY": "Oklahoma City",
        "VS_TEAM_NAME": "Thunder",
        "VS_TEAM_ABBREVIATION": "OKC",
        "STAT": "AST",
        "STAT_VALUE": 1,
        "STAT_ORDER": 5,
        "DATE_EST": "2025-03-03T00:00:00"
      },
      {
        "PLAYER_ID": 1642368,
        "GAME_ID": "0022500020",
        "GAME_DATE": "Oct 31 2025",
        "VS_TEAM_ID": 1610612754,
        "VS_TEAM_CITY": "Indiana",
        "VS_TEAM_NAME": "Pacers",
        "VS_TEAM_ABBREVIATION": "IND",
        "STAT": "STL",
        "STAT_VALUE": 1,
        "STAT_ORDER": 6,
        "DATE_EST": "2025-10-31T00:00:00"
      },
      {
        "PLAYER_ID": 1642368,
        "GAME_ID": "0022500101",
        "GAME_DATE": "Oct 25 2025",
        "VS_TEAM_ID": 1610612760,
        "VS_TEAM_CITY": "Oklahoma City",
        "VS_TEAM_NAME": "Thunder",
        "VS_TEAM_ABBREVIATION": "OKC",
        "STAT": "STL",
        "STAT_VALUE": 1,
        "STAT_ORDER": 6,
        "DATE_EST": "2025-10-25T00:00:00"
      },
      {
        "PLAYER_ID": 1642368,
        "GAME_ID": "0022401185",
        "GAME_DATE": "Apr 11 2025",
        "VS_TEAM_ID": 1610612747,
        "VS_TEAM_CITY": "Los Angeles",
        "VS_TEAM_NAME": "Lakers",
        "VS_TEAM_ABBREVIATION": "LAL",
        "STAT": "STL",
        "STAT_VALUE": 1,
        "STAT_ORDER": 6,
        "DATE_EST": "2025-04-11T00:00:00"
      },
      {
        "PLAYER_ID": 1642368,
        "GAME_ID": "0022401166",
        "GAME_DATE": "Apr 09 2025",
        "VS_TEAM_ID": 1610612746,
        "VS_TEAM_CITY": "LA",
        "VS_TEAM_NAME": "Clippers",
        "VS_TEAM_ABBREVIATION": "LAC",
        "STAT": "BLK",
        "STAT_VALUE": 2,
        "STAT_ORDER": 7,
        "DATE_EST": "2025-04-09T00:00:00"
      },
      {
        "PLAYER_ID": 1642368,
        "GAME_ID": "0022400879",
        "GAME_DATE": "Mar 03 2025",
        "VS_TEAM_ID": 1610612760,
        "VS_TEAM_CITY": "Oklahoma City",
        "VS_TEAM_NAME": "Thunder",
        "VS_TEAM_ABBREVIATION": "OKC",
        "STAT": "BLK",
        "STAT_VALUE": 2,
        "STAT_ORDER": 7,
        "DATE_EST": "2025-03-03T00:00:00"
      },
      {
        "PLAYER_ID": 1642368,
        "GAME_ID": "0022401185",
        "GAME_DATE": "Apr 11 2025",
        "VS_TEAM_ID": 1610612747,
        "VS_TEAM_CITY": "Los Angeles",
        "VS_TEAM_NAME": "Lakers",
        "VS_TEAM_ABBREVIATION": "LAL",
        "STAT": "FGM",
        "STAT_VALUE": 4,
        "STAT_ORDER": 8,
        "DATE_EST": "2025-04-11T00:00:00"
      },
      {
        "PLAYER_ID": 1642368,
        "GAME_ID": "0022400879",
        "GAME_DATE": "Mar 03 2025",
        "VS_TEAM_ID": 1610612760,
        "VS_TEAM_CITY": "Oklahoma City",
        "VS_TEAM_NAME": "Thunder",
        "VS_TEAM_ABBREVIATION": "OKC",
        "STAT": "FGM",
        "STAT_VALUE": 4,
        "STAT_ORDER": 8,
        "DATE_EST": "2025-03-03T00:00:00"
      },
      {
        "PLAYER_ID": 1642368,
        "GAME_ID": "0022400879",
        "GAME_DATE": "Mar 03 2025",
        "VS_TEAM_ID": 1610612760,
        "VS_TEAM_CITY": "Oklahoma City",
        "VS_TEAM_NAME": "Thunder",
        "VS_TEAM_ABBREVIATION": "OKC",
        "STAT": "FGA",
        "STAT_VALUE": 6,
        "STAT_ORDER": 9,
        "DATE_EST": "2025-03-03T00:00:00"
      },
      {
        "PLAYER_ID": 1642368,
        "GAME_ID": "0022500020",
        "GAME_DATE": "Oct 31 2025",
        "VS_TEAM_ID": 1610612754,
        "VS_TEAM_CITY": "Indiana",
        "VS_TEAM_NAME": "Pacers",
        "VS_TEAM_ABBREVIATION": "IND",
        "STAT": "FG3M",
        "STAT_VALUE": 0,
        "STAT_ORDER": 10,
        "DATE_EST": "2025-10-31T00:00:00"
      },
      {
        "PLAYER_ID": 1642368,
        "GAME_ID": "0022500101",
        "GAME_DATE": "Oct 25 2025",
        "VS_TEAM_ID": 1610612760,
        "VS_TEAM_CITY": "Oklahoma City",
        "VS_TEAM_NAME": "Thunder",
        "VS_TEAM_ABBREVIATION": "OKC",
        "STAT": "FG3M",
        "STAT_VALUE": 0,
        "STAT_ORDER": 10,
        "DATE_EST": "2025-10-25T00:00:00"
      },
      {
        "PLAYER_ID": 1642368,
        "GAME_ID": "0022500090",
        "GAME_DATE": "Oct 24 2025",
        "VS_TEAM_ID": 1610612753,
        "VS_TEAM_CITY": "Orlando",
        "VS_TEAM_NAME": "Magic",
        "VS_TEAM_ABBREVIATION": "ORL",
        "STAT": "FG3M",
        "STAT_VALUE": 0,
        "STAT_ORDER": 10,
        "DATE_EST": "2025-10-24T00:00:00"
      },
      {
        "PLAYER_ID": 1642368,
        "GAME_ID": "0022401193",
        "GAME_DATE": "Apr 13 2025",
        "VS_TEAM_ID": 1610612743,
        "VS_TEAM_CITY": "Denver",
        "VS_TEAM_NAME": "Nuggets",
        "VS_TEAM_ABBREVIATION": "DEN",
        "STAT": "FG3M",
        "STAT_VALUE": 0,
        "STAT_ORDER": 10,
        "DATE_EST": "2025-04-13T00:00:00"
      },
      {
        "PLAYER_ID": 1642368,
        "GAME_ID": "0022401185",
        "GAME_DATE": "Apr 11 2025",
        "VS_TEAM_ID": 1610612747,
        "VS_TEAM_CITY": "Los Angeles",
        "VS_TEAM_NAME": "Lakers",
        "VS_TEAM_ABBREVIATION": "LAL",
        "STAT": "FG3M",
        "STAT_VALUE": 0,
        "STAT_ORDER": 10,
        "DATE_EST": "2025-04-11T00:00:00"
      },
      {
        "PLAYER_ID": 1642368,
        "GAME_ID": "0022401166",
        "GAME_DATE": "Apr 09 2025",
        "VS_TEAM_ID": 1610612746,
        "VS_TEAM_CITY": "LA",
        "VS_TEAM_NAME": "Clippers",
        "VS_TEAM_ABBREVIATION": "LAC",
        "STAT": "FG3M",
        "STAT_VALUE": 0,
        "STAT_ORDER": 10,
        "DATE_EST": "2025-04-09T00:00:00"
      },
      {
        "PLAYER_ID": 1642368,
        "GAME_ID": "0022400879",
        "GAME_DATE": "Mar 03 2025",
        "VS_TEAM_ID": 1610612760,
        "VS_TEAM_CITY": "Oklahoma City",
        "VS_TEAM_NAME": "Thunder",
        "VS_TEAM_ABBREVIATION": "OKC",
        "STAT": "FG3M",
        "STAT_VALUE": 0,
        "STAT_ORDER": 10,
        "DATE_EST": "2025-03-03T00:00:00"
      },
      {
        "PLAYER_ID": 1642368,
        "GAME_ID": "0022500020",
        "GAME_DATE": "Oct 31 2025",
        "VS_TEAM_ID": 1610612754,
        "VS_TEAM_CITY": "Indiana",
        "VS_TEAM_NAME": "Pacers",
        "VS_TEAM_ABBREVIATION": "IND",
        "STAT": "FG3A",
        "STAT_VALUE": 0,
        "STAT_ORDER": 11,
        "DATE_EST": "2025-10-31T00:00:00"
      },
      {
        "PLAYER_ID": 1642368,
        "GAME_ID": "0022500101",
        "GAME_DATE": "Oct 25 2025",
        "VS_TEAM_ID": 1610612760,
        "VS_TEAM_CITY": "Oklahoma City",
        "VS_TEAM_NAME": "Thunder",
        "VS_TEAM_ABBREVIATION": "OKC",
        "STAT": "FG3A",
        "STAT_VALUE": 0,
        "STAT_ORDER": 11,
        "DATE_EST": "2025-10-25T00:00:00"
      },
      {
        "PLAYER_ID": 1642368,
        "GAME_ID": "0022500090",
        "GAME_DATE": "Oct 24 2025",
        "VS_TEAM_ID": 1610612753,
        "VS_TEAM_CITY": "Orlando",
        "VS_TEAM_NAME": "Magic",
        "VS_TEAM_ABBREVIATION": "ORL",
        "STAT": "FG3A",
        "STAT_VALUE": 0,
        "STAT_ORDER": 11,
        "DATE_EST": "2025-10-24T00:00:00"
      },
      {
        "PLAYER_ID": 1642368,
        "GAME_ID": "0022401193",
        "GAME_DATE": "Apr 13 2025",
        "VS_TEAM_ID": 1610612743,
        "VS_TEAM_CITY": "Denver",
        "VS_TEAM_NAME": "Nuggets",
        "VS_TEAM_ABBREVIATION": "DEN",
        "STAT": "FG3A",
        "STAT_VALUE": 0,
        "STAT_ORDER": 11,
        "DATE_EST": "2025-04-13T00:00:00"
      },
      {
        "PLAYER_ID": 1642368,
        "GAME_ID": "0022401185",
        "GAME_DATE": "Apr 11 2025",
        "VS_TEAM_ID": 1610612747,
        "VS_TEAM_CITY": "Los Angeles",
        "VS_TEAM_NAME": "Lakers",
        "VS_TEAM_ABBREVIATION": "LAL",
        "STAT": "FG3A",
        "STAT_VALUE": 0,
        "STAT_ORDER": 11,
        "DATE_EST": "2025-04-11T00:00:00"
      },
      {
        "PLAYER_ID": 1642368,
        "GAME_ID": "0022401166",
        "GAME_DATE": "Apr 09 2025",
        "VS_TEAM_ID": 1610612746,
        "VS_TEAM_CITY": "LA",
        "VS_TEAM_NAME": "Clippers",
        "VS_TEAM_ABBREVIATION": "LAC",
        "STAT": "FG3A",
        "STAT_VALUE": 0,
        "STAT_ORDER": 11,
        "DATE_EST": "2025-04-09T00:00:00"
      },
      {
        "PLAYER_ID": 1642368,
        "GAME_ID": "0022400879",
        "GAME_DATE": "Mar 03 2025",
        "VS_TEAM_ID": 1610612760,
        "VS_TEAM_CITY": "Oklahoma City",
        "VS_TEAM_NAME": "Thunder",
        "VS_TEAM_ABBREVIATION": "OKC",
        "STAT": "FG3A",
        "STAT_VALUE": 0,
        "STAT_ORDER": 11,
        "DATE_EST": "2025-03-03T00:00:00"
      },
      {
        "PLAYER_ID": 1642368,
        "GAME_ID": "0022401166",
        "GAME_DATE": "Apr 09 2025",
        "VS_TEAM_ID": 1610612746,
        "VS_TEAM_CITY": "LA",
        "VS_TEAM_NAME": "Clippers",
        "VS_TEAM_ABBREVIATION": "LAC",
        "STAT": "FTM",
        "STAT_VALUE": 2,
        "STAT_ORDER": 12,
        "DATE_EST": "2025-04-09T00:00:00"
      },
      {
        "PLAYER_ID": 1642368,
        "GAME_ID": "0022400879",
        "GAME_DATE": "Mar 03 2025",
        "VS_TEAM_ID": 1610612760,
        "VS_TEAM_CITY": "Oklahoma City",
        "VS_TEAM_NAME": "Thunder",
        "VS_TEAM_ABBREVIATION": "OKC",
        "STAT": "FTM",
        "STAT_VALUE": 2,
        "STAT_ORDER": 12,
        "DATE_EST": "2025-03-03T00:00:00"
      },
      {
        "PLAYER_ID": 1642368,
        "GAME_ID": "0022400879",
        "GAME_DATE": "Mar 03 2025",
        "VS_TEAM_ID": 1610612760,
        "VS_TEAM_CITY": "Oklahoma City",
        "VS_TEAM_NAME": "Thunder",
        "VS_TEAM_ABBREVIATION": "OKC",
        "STAT": "FTA",
        "STAT_VALUE": 3,
        "STAT_ORDER": 13,
        "DATE_EST": "2025-03-03T00:00:00"
      }
    ]
  }
}